{
	"code": 2,
	"msg": "接口调用成功",
	"page": {
		"allPageSize": 6,
		"allRecordSize": 59,
		"pageRecodeSize": 10,
		"restCount": 0
	},
	"data": {
		"totalCount": 59,
		"pageIndex": 1,
		"pageSize": 10,
		"dataList": [
			{
				"id": 1,
				"orderNo": "201908081121",
				"createTime": "2019-09-27 20:35:06",
				"rootCategory": "咨询订单",
				"childCategory": "语音咨询",
				"status": "已完成",
				"amount": "140"
			},
			{
				"id": 2,
				"orderNo": "201908081121",
				"createTime": "2019-09-27 20:35:06",
				"rootCategory": "法律服务",
				"childCategory": "非诉讼法律服务",
				"status": "已完成",
				"amount": "140"
			},
			{
				"id": 3,
				"orderNo": "201908081121",
				"createTime": "2019-09-27 20:35:06",
				"rootCategory": "法律文件",
				"childCategory": "劳务合同",
				"status": "已完成",
				"amount": "140"
			},
			{
				"id": 4,
				"orderNo": "201908081121",
				"createTime": "2019-09-27 20:35:06",
				"rootCategory": "代理律师",
				"childCategory": "语音咨询",
				"status": "已完成",
				"amount": "140"
			},
			{
				"id": 5,
				"orderNo": "201908081121",
				"createTime": "2019-09-27 20:35:06",
				"rootCategory": "咨询订单",
				"childCategory": "1对1咨询",
				"status": "已完成",
				"amount": "140"
			},
			{
				"id": 6,
				"orderNo": "201908081121",
				"createTime": "2019-09-27 20:35:06",
				"rootCategory": "咨询订单",
				"childCategory": "语音咨询",
				"status": "已完成",
				"amount": "140"
			},
			{
				"id": 7,
				"orderNo": "201908081121",
				"createTime": "2019-09-27 20:35:06",
				"rootCategory": "法律服务",
				"childCategory": "非诉讼法律服务",
				"status": "已完成",
				"amount": "140"
			},
			{
				"id": 8,
				"orderNo": "201908081121",
				"createTime": "2019-09-27 20:35:06",
				"rootCategory": "法律文件",
				"childCategory": "劳务合同",
				"status": "已完成",
				"amount": "140"
			},
			{
				"id": 9,
				"orderNo": "201908081121",
				"createTime": "2019-09-27 20:35:06",
				"rootCategory": "代理律师",
				"childCategory": "语音咨询",
				"status": "已完成",
				"amount": "140"
			},
			{
				"id": 10,
				"orderNo": "201908081121",
				"createTime": "2019-09-27 20:35:06",
				"rootCategory": "咨询订单",
				"childCategory": "1对1咨询",
				"status": "已完成",
				"amount": "140"
			}
		],
		"fromIndex": 0,
		"toIndex": 10,
		"pageCount": 6
	}
}